ymapi/__init__.py
ymapi-0.0.1.dist-info/METADATA
ymapi-0.0.1.dist-info/WHEEL
ymapi-0.0.1.dist-info/entry_points.txt
ymapi-0.0.1.dist-info/RECORD
