Metadata-Version: 2.4
Name: ymapi
Version: 0.0.1
Summary: Thin wrapper for Yandex.Market API
Author-email: Dmitry Drozdov <ds.drozdov@gmail.com>
Requires-Python: >=3.13
